jepartapp/__init__.py
jepartapp-1.0.7.dist-info/WHEEL
jepartapp-1.0.7.dist-info/METADATA
jepartapp-1.0.7.dist-info/RECORD
