Metadata-Version: 2.1
Name: jepartapp
Version: 1.0.7
Summary: Criado para envio e atualiçaõ de informações de loja fisica para servidor online.
Author: Jean Carlos
Author-email: jeancarlosjc210995@gmail.com
Requires-Python: >=3.10,<4.0
Classifier: Programming Language :: Python :: 3
Classifier: Programming Language :: Python :: 3.10
